energiinfo/__init__.py
energiinfo/api.py
energiinfo/const.py
energiinfo-1.0.4.dist-info/LICENSE
energiinfo-1.0.4.dist-info/METADATA
energiinfo-1.0.4.dist-info/WHEEL
energiinfo-1.0.4.dist-info/top_level.txt
energiinfo-1.0.4.dist-info/RECORD
