Metadata-Version: 2.1
Name: energiinfo
Version: 1.0.4
Summary: Energiinfo API package
Home-page: https://gitlab.com/veulsan/energiinfo
Author: Ulrik Sannsell
Author-email: ulrik@sannsell.se
Project-URL: Bug Tracker, https://gitlab.com/veulsan/energiinfo/-/issues
Project-URL: repository, https://gitlab.com/veulsan/energiinfo
Classifier: Programming Language :: Python :: 3
Classifier: License :: OSI Approved :: MIT License
Classifier: Operating System :: OS Independent
Requires-Python: >=3.6
License-File: LICENSE
